{"statuses":[{"metadata":{"iso_language_code":"de","result_type":"recent"},"created_at":"Fri Mar 13 21:46:40 +0000 2015","id":576499643120381953,"id_str":"576499643120381953","text":"Hasseblad 500 CM, Portra 160\n#filmisnotdead @ Pinhole Coffee https:\/\/t.co\/I3O0zu49OS","source":"\u003ca href=\"http:\/\/instagram.com\" rel=\"nofollow\"\u003eInstagram\u003c\/a\u003e","truncated":false,"in_reply_to_status_id":null,"in_reply_to_status_id_str":null,"in_reply_to_user_id":null,"in_reply_to_user_id_str":null,"in_reply_to_screen_name":null,"user":{"id":269550899,"id_str":"269550899","name":"Travis Hallmark","screen_name":"travishallmark","location":"","profile_location":null,"description":"|Photographer|Coffee Homebrewer|Bike Builder\/Rider|Faith Led Adventurer|","url":"http:\/\/t.co\/fogzVJIV1n","entities":{"url":{"urls":[{"url":"http:\/\/t.co\/fogzVJIV1n","expanded_url":"http:\/\/travishallmark.co","display_url":"travishallmark.co","indices":[0,22]}]},"description":{"urls":[]}},"protected":false,"followers_count":360,"friends_count":491,"listed_count":7,"created_at":"Mon Mar 21 00:52:13 +0000 2011","favourites_count":2984,"utc_offset":-18000,"time_zone":"Central Time (US & Canada)","geo_enabled":true,"verified":false,"statuses_count":6758,"lang":"en","contributors_enabled":false,"is_translator":false,"is_translation_enabled":false,"profile_background_color":"F01136","profile_background_image_url":"http:\/\/abs.twimg.com\/images\/themes\/theme18\/bg.gif","profile_background_image_url_https":"https:\/\/abs.twimg.com\/images\/themes\/theme18\/bg.gif","profile_background_tile":false,"profile_image_url":"http:\/\/pbs.twimg.com\/profile_images\/558461250808848384\/H-8UB3dv_normal.jpeg","profile_image_url_https":"https:\/\/pbs.twimg.com\/profile_images\/558461250808848384\/H-8UB3dv_normal.jpeg","profile_banner_url":"https:\/\/pbs.twimg.com\/profile_banners\/269550899\/1421982776","profile_link_color":"09E811","profile_sidebar_border_color":"0AF511","profile_sidebar_fill_color":"0A090A","profile_text_color":"FFFAFF","profile_use_background_image":true,"default_profile":false,"default_profile_image":false,"following":false,"follow_request_sent":false,"notifications":false},"geo":{"type":"Point","coordinates":[37.739681,-122.418961]},"coordinates":{"type":"Point","coordinates":[-122.418961,37.739681]},"place":{"id":"5a110d312052166f","url":"https:\/\/api.twitter.com\/1.1\/geo\/id\/5a110d312052166f.json","place_type":"city","name":"San Francisco","full_name":"San Francisco, CA","country_code":"US","country":"United States","contained_within":[],"bounding_box":{"type":"Polygon","coordinates":[[[-122.514926,37.708075],[-122.357031,37.708075],[-122.357031,37.833238],[-122.514926,37.833238]]]},"attributes":{}},"contributors":null,"retweet_count":0,"favorite_count":0,"entities":{"hashtags":[{"text":"filmisnotdead","indices":[29,43]}],"symbols":[],"user_mentions":[],"urls":[{"url":"https:\/\/t.co\/I3O0zu49OS","expanded_url":"https:\/\/instagram.com\/p\/0LvjKzrRVF\/","display_url":"instagram.com\/p\/0LvjKzrRVF\/","indices":[61,84]}]},"favorited":false,"retweeted":false,"possibly_sensitive":false,"lang":"de"},{"metadata":{"iso_language_code":"en","result_type":"recent"},"created_at":"Fri Mar 13 21:46:18 +0000 2015","id":576499553240662016,"id_str":"576499553240662016","text":"Entry Level Legal Positions - Robert Half Legal: (#SanFrancisco, CA) http:\/\/t.co\/qbp2R5rupA #Clerical #Job #Jobs #TweetMyJobs","source":"\u003ca href=\"http:\/\/www.tweetmyjobs.com\" rel=\"nofollow\"\u003eTweetMyJOBS\u003c\/a\u003e","truncated":false,"in_reply_to_status_id":null,"in_reply_to_status_id_str":null,"in_reply_to_user_id":null,"in_reply_to_user_id_str":null,"in_reply_to_screen_name":null,"user":{"id":22966544,"id_str":"22966544","name":"TMJ-SFO Cleric. Jobs","screen_name":"tmj_sfo_cler","location":"San Francisco, CA","profile_location":null,"description":"Follow this account for geo-targeted Office\/Clerical job tweets in San Francisco, CA. Need help? Tweet us at @TweetMyJobs!","url":"http:\/\/t.co\/p7ZTFqGHJf","entities":{"url":{"urls":[{"url":"http:\/\/t.co\/p7ZTFqGHJf","expanded_url":"http:\/\/tweetmyjobs.com","display_url":"tweetmyjobs.com","indices":[0,22]}]},"description":{"urls":[]}},"protected":false,"followers_count":374,"friends_count":233,"listed_count":8,"created_at":"Thu Mar 05 19:44:20 +0000 2009","favourites_count":0,"utc_offset":-14400,"time_zone":"Eastern Time (US & Canada)","geo_enabled":true,"verified":false,"statuses_count":322,"lang":"en","contributors_enabled":false,"is_translator":false,"is_translation_enabled":false,"profile_background_color":"253956","profile_background_image_url":"http:\/\/pbs.twimg.com\/profile_background_images\/315528242\/Twitter-BG_2_bg-image.jpg","profile_background_image_url_https":"https:\/\/pbs.twimg.com\/profile_background_images\/315528242\/Twitter-BG_2_bg-image.jpg","profile_background_tile":false,"profile_image_url":"http:\/\/pbs.twimg.com\/profile_images\/2303738182\/Logo_tmj_new2b_normal.png","profile_image_url_https":"https:\/\/pbs.twimg.com\/profile_images\/2303738182\/Logo_tmj_new2b_normal.png","profile_banner_url":"https:\/\/pbs.twimg.com\/profile_banners\/22966544\/1349362179","profile_link_color":"96BEDF","profile_sidebar_border_color":"000000","profile_sidebar_fill_color":"407DB0","profile_text_color":"000000","profile_use_background_image":true,"default_profile":false,"default_profile_image":false,"following":false,"follow_request_sent":false,"notifications":false},"geo":{"type":"Point","coordinates":[37.7749295,-122.4194155]},"coordinates":{"type":"Point","coordinates":[-122.4194155,37.7749295]},"place":{"id":"5a110d312052166f","url":"https:\/\/api.twitter.com\/1.1\/geo\/id\/5a110d312052166f.json","place_type":"city","name":"San Francisco","full_name":"San Francisco, CA","country_code":"US","country":"United States","contained_within":[],"bounding_box":{"type":"Polygon","coordinates":[[[-122.514926,37.708075],[-122.357031,37.708075],[-122.357031,37.833238],[-122.514926,37.833238]]]},"attributes":{}},"contributors":null,"retweet_count":0,"favorite_count":0,"entities":{"hashtags":[{"text":"SanFrancisco","indices":[50,63]},{"text":"Clerical","indices":[92,101]},{"text":"Job","indices":[102,106]},{"text":"Jobs","indices":[107,112]},{"text":"TweetMyJobs","indices":[113,125]}],"symbols":[],"user_mentions":[],"urls":[{"url":"http:\/\/t.co\/qbp2R5rupA","expanded_url":"http:\/\/bit.ly\/1Ax6cOG","display_url":"bit.ly\/1Ax6cOG","indices":[69,91]}]},"favorited":false,"retweeted":false,"possibly_sensitive":false,"lang":"en"},{"metadata":{"iso_language_code":"en","result_type":"recent"},"created_at":"Fri Mar 13 21:46:17 +0000 2015","id":576499546030665729,"id_str":"576499546030665729","text":"This morning @ Union Square, San Francisco https:\/\/t.co\/ObR3RT3PY5","source":"\u003ca href=\"http:\/\/instagram.com\" rel=\"nofollow\"\u003eInstagram\u003c\/a\u003e","truncated":false,"in_reply_to_status_id":null,"in_reply_to_status_id_str":null,"in_reply_to_user_id":null,"in_reply_to_user_id_str":null,"in_reply_to_screen_name":null,"user":{"id":16526794,"id_str":"16526794","name":"Jesse English","screen_name":"jrenglish","location":"tallahassee, fl","profile_location":null,"description":"","url":"http:\/\/t.co\/g9zssX2s9h","entities":{"url":{"urls":[{"url":"http:\/\/t.co\/g9zssX2s9h","expanded_url":"http:\/\/jrenglish.tumblr.com","display_url":"jrenglish.tumblr.com","indices":[0,22]}]},"description":{"urls":[]}},"protected":false,"followers_count":163,"friends_count":112,"listed_count":10,"created_at":"Tue Sep 30 12:16:56 +0000 2008","favourites_count":88,"utc_offset":-18000,"time_zone":"Central Time (US & Canada)","geo_enabled":true,"verified":false,"statuses_count":12038,"lang":"en","contributors_enabled":false,"is_translator":false,"is_translation_enabled":false,"profile_background_color":"1A1B1F","profile_background_image_url":"http:\/\/abs.twimg.com\/images\/themes\/theme9\/bg.gif","profile_background_image_url_https":"https:\/\/abs.twimg.com\/images\/themes\/theme9\/bg.gif","profile_background_tile":false,"profile_image_url":"http:\/\/pbs.twimg.com\/profile_images\/488686489253867521\/7juu4ATf_normal.jpeg","profile_image_url_https":"https:\/\/pbs.twimg.com\/profile_images\/488686489253867521\/7juu4ATf_normal.jpeg","profile_link_color":"2FC2EF","profile_sidebar_border_color":"181A1E","profile_sidebar_fill_color":"252429","profile_text_color":"666666","profile_use_background_image":true,"default_profile":false,"default_profile_image":false,"following":false,"follow_request_sent":false,"notifications":false},"geo":{"type":"Point","coordinates":[37.78703027,-122.40755291]},"coordinates":{"type":"Point","coordinates":[-122.40755291,37.78703027]},"place":{"id":"5a110d312052166f","url":"https:\/\/api.twitter.com\/1.1\/geo\/id\/5a110d312052166f.json","place_type":"city","name":"San Francisco","full_name":"San Francisco, CA","country_code":"US","country":"United States","contained_within":[],"bounding_box":{"type":"Polygon","coordinates":[[[-122.514926,37.708075],[-122.357031,37.708075],[-122.357031,37.833238],[-122.514926,37.833238]]]},"attributes":{}},"contributors":null,"retweet_count":0,"favorite_count":0,"entities":{"hashtags":[],"symbols":[],"user_mentions":[],"urls":[{"url":"https:\/\/t.co\/ObR3RT3PY5","expanded_url":"https:\/\/instagram.com\/p\/0LvgUorlaE\/","display_url":"instagram.com\/p\/0LvgUorlaE\/","indices":[43,66]}]},"favorited":false,"retweeted":false,"possibly_sensitive":false,"lang":"en"},{"metadata":{"iso_language_code":"und","result_type":"recent"},"created_at":"Fri Mar 13 21:46:08 +0000 2015","id":576499508487434240,"id_str":"576499508487434240","text":"@stevewells89 \ud83c\udf34\ud83d\udc4d","source":"\u003ca href=\"http:\/\/twitter.com\/download\/android\" rel=\"nofollow\"\u003eTwitter for Android\u003c\/a\u003e","truncated":false,"in_reply_to_status_id":576499001081663489,"in_reply_to_status_id_str":"576499001081663489","in_reply_to_user_id":2821834741,"in_reply_to_user_id_str":"2821834741","in_reply_to_screen_name":"stevewells89","user":{"id":98743946,"id_str":"98743946","name":"   \u270c NIA DINERO\u270c","screen_name":"Nia_Dinero","location":"Northern VA\u270c","profile_location":null,"description":"DON'T TELL THEM YOU'RE COMING, JUST ARRIVE+ For Booking\/Features: J.Allen@sosamusicgroup.com","url":"http:\/\/t.co\/H33JVJZnzJ","entities":{"url":{"urls":[{"url":"http:\/\/t.co\/H33JVJZnzJ","expanded_url":"http:\/\/youtu.be\/nEItf8kHfeE","display_url":"youtu.be\/nEItf8kHfeE","indices":[0,22]}]},"description":{"urls":[]}},"protected":false,"followers_count":2616,"friends_count":2879,"listed_count":3,"created_at":"Tue Dec 22 23:26:50 +0000 2009","favourites_count":12,"utc_offset":-18000,"time_zone":"Central Time (US & Canada)","geo_enabled":true,"verified":false,"statuses_count":4392,"lang":"en","contributors_enabled":false,"is_translator":false,"is_translation_enabled":false,"profile_background_color":"022330","profile_background_image_url":"http:\/\/pbs.twimg.com\/profile_background_images\/887726714\/1f37e08cb91ed7c5a1f12e011b340c79.jpeg","profile_background_image_url_https":"https:\/\/pbs.twimg.com\/profile_background_images\/887726714\/1f37e08cb91ed7c5a1f12e011b340c79.jpeg","profile_background_tile":true,"profile_image_url":"http:\/\/pbs.twimg.com\/profile_images\/572190880980983811\/L96JkHJB_normal.jpeg","profile_image_url_https":"https:\/\/pbs.twimg.com\/profile_images\/572190880980983811\/L96JkHJB_normal.jpeg","profile_banner_url":"https:\/\/pbs.twimg.com\/profile_banners\/98743946\/1422455455","profile_link_color":"0084B4","profile_sidebar_border_color":"FFFFFF","profile_sidebar_fill_color":"C0DFEC","profile_text_color":"333333","profile_use_background_image":true,"default_profile":false,"default_profile_image":false,"following":false,"follow_request_sent":false,"notifications":false},"geo":{"type":"Point","coordinates":[37.8011954,-122.4250015]},"coordinates":{"type":"Point","coordinates":[-122.4250015,37.8011954]},"place":{"id":"5a110d312052166f","url":"https:\/\/api.twitter.com\/1.1\/geo\/id\/5a110d312052166f.json","place_type":"city","name":"San Francisco","full_name":"San Francisco, CA","country_code":"US","country":"United States","contained_within":[],"bounding_box":{"type":"Polygon","coordinates":[[[-122.514926,37.708075],[-122.357031,37.708075],[-122.357031,37.833238],[-122.514926,37.833238]]]},"attributes":{}},"contributors":null,"retweet_count":0,"favorite_count":0,"entities":{"hashtags":[],"symbols":[],"user_mentions":[{"screen_name":"stevewells89","name":"Steve wells","id":2821834741,"id_str":"2821834741","indices":[0,13]}],"urls":[]},"favorited":false,"retweeted":false,"lang":"und"},{"metadata":{"iso_language_code":"und","result_type":"recent"},"created_at":"Fri Mar 13 21:45:55 +0000 2015","id":576499454758502400,"id_str":"576499454758502400","text":"\ud83d\udd3d\n\ud83d\udd3c\n#Architecture #reflex #skyporn #SF #SanFrancisco #CA #Tower #instago #instagood #instalike\u2026 https:\/\/t.co\/z9r0N1PXqb","source":"\u003ca href=\"http:\/\/instagram.com\" rel=\"nofollow\"\u003eInstagram\u003c\/a\u003e","truncated":false,"in_reply_to_status_id":null,"in_reply_to_status_id_str":null,"in_reply_to_user_id":null,"in_reply_to_user_id_str":null,"in_reply_to_screen_name":null,"user":{"id":62702051,"id_str":"62702051","name":"Nicolas Fil Backal","screen_name":"NBFil","location":"Mexico city","profile_location":null,"description":"Professional architect, graphic design enthusiast, and passionate for photography.","url":"http:\/\/t.co\/UXmFgnAcGY","entities":{"url":{"urls":[{"url":"http:\/\/t.co\/UXmFgnAcGY","expanded_url":"http:\/\/www.n-ba.mx","display_url":"n-ba.mx","indices":[0,22]}]},"description":{"urls":[]}},"protected":false,"followers_count":95,"friends_count":197,"listed_count":3,"created_at":"Tue Aug 04 03:09:12 +0000 2009","favourites_count":48,"utc_offset":null,"time_zone":null,"geo_enabled":true,"verified":false,"statuses_count":585,"lang":"en","contributors_enabled":false,"is_translator":false,"is_translation_enabled":false,"profile_background_color":"4A4A4A","profile_background_image_url":"http:\/\/pbs.twimg.com\/profile_background_images\/557373159\/DSC_0117.jpg","profile_background_image_url_https":"https:\/\/pbs.twimg.com\/profile_background_images\/557373159\/DSC_0117.jpg","profile_background_tile":false,"profile_image_url":"http:\/\/pbs.twimg.com\/profile_images\/1863198327\/419763_10150501271552750_511152749_9235811_1700195478_n_normal.jpg","profile_image_url_https":"https:\/\/pbs.twimg.com\/profile_images\/1863198327\/419763_10150501271552750_511152749_9235811_1700195478_n_normal.jpg","profile_banner_url":"https:\/\/pbs.twimg.com\/profile_banners\/62702051\/1421866069","profile_link_color":"FFCC4D","profile_sidebar_border_color":"EDF6F5","profile_sidebar_fill_color":"C9D7D7","profile_text_color":"FF6600","profile_use_background_image":true,"default_profile":false,"default_profile_image":false,"following":false,"follow_request_sent":false,"notifications":false},"geo":{"type":"Point","coordinates":[37.77841621,-122.38975127]},"coordinates":{"type":"Point","coordinates":[-122.38975127,37.77841621]},"place":{"id":"5a110d312052166f","url":"https:\/\/api.twitter.com\/1.1\/geo\/id\/5a110d312052166f.json","place_type":"city","name":"San Francisco","full_name":"San Francisco, CA","country_code":"US","country":"United States","contained_within":[],"bounding_box":{"type":"Polygon","coordinates":[[[-122.514926,37.708075],[-122.357031,37.708075],[-122.357031,37.833238],[-122.514926,37.833238]]]},"attributes":{}},"contributors":null,"retweet_count":0,"favorite_count":0,"entities":{"hashtags":[{"text":"Architecture","indices":[4,17]},{"text":"reflex","indices":[18,25]},{"text":"skyporn","indices":[26,34]},{"text":"SF","indices":[35,38]},{"text":"SanFrancisco","indices":[39,52]},{"text":"CA","indices":[53,56]},{"text":"Tower","indices":[57,63]},{"text":"instago","indices":[64,72]},{"text":"instagood","indices":[73,83]},{"text":"instalike","indices":[84,94]}],"symbols":[],"user_mentions":[],"urls":[{"url":"https:\/\/t.co\/z9r0N1PXqb","expanded_url":"https:\/\/instagram.com\/p\/0LvdtQuZty\/","display_url":"instagram.com\/p\/0LvdtQuZty\/","indices":[96,119]}]},"favorited":false,"retweeted":false,"possibly_sensitive":false,"lang":"und"},{"metadata":{"iso_language_code":"en","result_type":"recent"},"created_at":"Fri Mar 13 21:45:47 +0000 2015","id":576499420721713152,"id_str":"576499420721713152","text":"Pure beauty without a word! @ Filbert Steps https:\/\/t.co\/V9BYcLck7U","source":"\u003ca href=\"http:\/\/instagram.com\" rel=\"nofollow\"\u003eInstagram\u003c\/a\u003e","truncated":false,"in_reply_to_status_id":null,"in_reply_to_status_id_str":null,"in_reply_to_user_id":null,"in_reply_to_user_id_str":null,"in_reply_to_screen_name":null,"user":{"id":712805234,"id_str":"712805234","name":"Kathy Tian","screen_name":"tiankez0806","location":"San Francisco","profile_location":null,"description":"","url":null,"entities":{"description":{"urls":[]}},"protected":false,"followers_count":36,"friends_count":254,"listed_count":0,"created_at":"Mon Jul 23 17:39:44 +0000 2012","favourites_count":28,"utc_offset":null,"time_zone":null,"geo_enabled":true,"verified":false,"statuses_count":119,"lang":"en","contributors_enabled":false,"is_translator":false,"is_translation_enabled":false,"profile_background_color":"000000","profile_background_image_url":"http:\/\/abs.twimg.com\/images\/themes\/theme1\/bg.png","profile_background_image_url_https":"https:\/\/abs.twimg.com\/images\/themes\/theme1\/bg.png","profile_background_tile":false,"profile_image_url":"http:\/\/pbs.twimg.com\/profile_images\/538581403609231362\/AH-uYt0a_normal.jpeg","profile_image_url_https":"https:\/\/pbs.twimg.com\/profile_images\/538581403609231362\/AH-uYt0a_normal.jpeg","profile_link_color":"EEEEEE","profile_sidebar_border_color":"000000","profile_sidebar_fill_color":"000000","profile_text_color":"000000","profile_use_background_image":false,"default_profile":false,"default_profile_image":false,"following":false,"follow_request_sent":false,"notifications":false},"geo":{"type":"Point","coordinates":[37.80208951,-122.40397280]},"coordinates":{"type":"Point","coordinates":[-122.40397280,37.80208951]},"place":{"id":"5a110d312052166f","url":"https:\/\/api.twitter.com\/1.1\/geo\/id\/5a110d312052166f.json","place_type":"city","name":"San Francisco","full_name":"San Francisco, CA","country_code":"US","country":"United States","contained_within":[],"bounding_box":{"type":"Polygon","coordinates":[[[-122.514926,37.708075],[-122.357031,37.708075],[-122.357031,37.833238],[-122.514926,37.833238]]]},"attributes":{}},"contributors":null,"retweet_count":0,"favorite_count":0,"entities":{"hashtags":[],"symbols":[],"user_mentions":[],"urls":[{"url":"https:\/\/t.co\/V9BYcLck7U","expanded_url":"https:\/\/instagram.com\/p\/0Lvcu7Ot_u\/","display_url":"instagram.com\/p\/0Lvcu7Ot_u\/","indices":[44,67]}]},"favorited":false,"retweeted":false,"possibly_sensitive":false,"lang":"en"},{"metadata":{"iso_language_code":"en","result_type":"recent"},"created_at":"Fri Mar 13 21:45:27 +0000 2015","id":576499338081357824,"id_str":"576499338081357824","text":"TGIF! Got weekend plans? @otgsf will be in the Presidio on Sunday... Just sayin' @ Off the Grid:\u2026 https:\/\/t.co\/A0JyUh4I6k","source":"\u003ca href=\"http:\/\/instagram.com\" rel=\"nofollow\"\u003eInstagram\u003c\/a\u003e","truncated":false,"in_reply_to_status_id":null,"in_reply_to_status_id_str":null,"in_reply_to_user_id":null,"in_reply_to_user_id_str":null,"in_reply_to_screen_name":null,"user":{"id":28179049,"id_str":"28179049","name":"Yelp SF - Abby S","screen_name":"yelpsf","location":"San Francisco","profile_location":null,"description":"Yelp Community happenings in the heart of San Francisco. Sharing the local love!","url":"http:\/\/t.co\/uabPo3M7KF","entities":{"url":{"urls":[{"url":"http:\/\/t.co\/uabPo3M7KF","expanded_url":"http:\/\/yelp.com","display_url":"yelp.com","indices":[0,22]}]},"description":{"urls":[]}},"protected":false,"followers_count":5495,"friends_count":714,"listed_count":472,"created_at":"Wed Apr 01 19:51:50 +0000 2009","favourites_count":164,"utc_offset":-25200,"time_zone":"Pacific Time (US & Canada)","geo_enabled":true,"verified":false,"statuses_count":1707,"lang":"en","contributors_enabled":false,"is_translator":false,"is_translation_enabled":false,"profile_background_color":"9AE4E8","profile_background_image_url":"http:\/\/pbs.twimg.com\/profile_background_images\/7321892\/2899645199_4d73114494.jpg","profile_background_image_url_https":"https:\/\/pbs.twimg.com\/profile_background_images\/7321892\/2899645199_4d73114494.jpg","profile_background_tile":false,"profile_image_url":"http:\/\/pbs.twimg.com\/profile_images\/535159265951227904\/UIW448xt_normal.jpeg","profile_image_url_https":"https:\/\/pbs.twimg.com\/profile_images\/535159265951227904\/UIW448xt_normal.jpeg","profile_banner_url":"https:\/\/pbs.twimg.com\/profile_banners\/28179049\/1397693464","profile_link_color":"100147","profile_sidebar_border_color":"FFFFFF","profile_sidebar_fill_color":"BF0707","profile_text_color":"000000","profile_use_background_image":false,"default_profile":false,"default_profile_image":false,"following":false,"follow_request_sent":false,"notifications":false},"geo":{"type":"Point","coordinates":[37.80068863,-122.45821177]},"coordinates":{"type":"Point","coordinates":[-122.45821177,37.80068863]},"place":{"id":"5a110d312052166f","url":"https:\/\/api.twitter.com\/1.1\/geo\/id\/5a110d312052166f.json","place_type":"city","name":"San Francisco","full_name":"San Francisco, CA","country_code":"US","country":"United States","contained_within":[],"bounding_box":{"type":"Polygon","coordinates":[[[-122.514926,37.708075],[-122.357031,37.708075],[-122.357031,37.833238],[-122.514926,37.833238]]]},"attributes":{}},"contributors":null,"retweet_count":1,"favorite_count":0,"entities":{"hashtags":[],"symbols":[],"user_mentions":[{"screen_name":"otgsf","name":"Off the Grid","id":56779059,"id_str":"56779059","indices":[25,31]}],"urls":[{"url":"https:\/\/t.co\/A0JyUh4I6k","expanded_url":"https:\/\/instagram.com\/p\/0LvaUjg9Dw\/","display_url":"instagram.com\/p\/0LvaUjg9Dw\/","indices":[98,121]}]},"favorited":false,"retweeted":false,"possibly_sensitive":false,"lang":"en"},{"metadata":{"iso_language_code":"en","result_type":"recent"},"created_at":"Fri Mar 13 21:45:20 +0000 2015","id":576499306217091072,"id_str":"576499306217091072","text":"Thanks for lunch @dha!  \ud83d\ude03","source":"\u003ca href=\"http:\/\/twitter.com\/download\/iphone\" rel=\"nofollow\"\u003eTwitter for iPhone\u003c\/a\u003e","truncated":false,"in_reply_to_status_id":null,"in_reply_to_status_id_str":null,"in_reply_to_user_id":null,"in_reply_to_user_id_str":null,"in_reply_to_screen_name":null,"user":{"id":2480658211,"id_str":"2480658211","name":"Matt","screen_name":"mattvandeberg","location":"","profile_location":null,"description":"","url":null,"entities":{"description":{"urls":[]}},"protected":false,"followers_count":49,"friends_count":98,"listed_count":1,"created_at":"Tue May 06 22:59:50 +0000 2014","favourites_count":639,"utc_offset":null,"time_zone":null,"geo_enabled":true,"verified":false,"statuses_count":233,"lang":"en","contributors_enabled":false,"is_translator":false,"is_translation_enabled":false,"profile_background_color":"C0DEED","profile_background_image_url":"http:\/\/abs.twimg.com\/images\/themes\/theme1\/bg.png","profile_background_image_url_https":"https:\/\/abs.twimg.com\/images\/themes\/theme1\/bg.png","profile_background_tile":false,"profile_image_url":"http:\/\/pbs.twimg.com\/profile_images\/463817228983341057\/LeNXw0mP_normal.jpeg","profile_image_url_https":"https:\/\/pbs.twimg.com\/profile_images\/463817228983341057\/LeNXw0mP_normal.jpeg","profile_link_color":"0084B4","profile_sidebar_border_color":"C0DEED","profile_sidebar_fill_color":"DDEEF6","profile_text_color":"333333","profile_use_background_image":true,"default_profile":true,"default_profile_image":false,"following":false,"follow_request_sent":false,"notifications":false},"geo":{"type":"Point","coordinates":[37.79021835,-122.39321302]},"coordinates":{"type":"Point","coordinates":[-122.39321302,37.79021835]},"place":{"id":"5a110d312052166f","url":"https:\/\/api.twitter.com\/1.1\/geo\/id\/5a110d312052166f.json","place_type":"city","name":"San Francisco","full_name":"San Francisco, CA","country_code":"US","country":"United States","contained_within":[],"bounding_box":{"type":"Polygon","coordinates":[[[-122.514926,37.708075],[-122.357031,37.708075],[-122.357031,37.833238],[-122.514926,37.833238]]]},"attributes":{}},"contributors":null,"retweet_count":0,"favorite_count":0,"entities":{"hashtags":[],"symbols":[],"user_mentions":[{"screen_name":"dha","name":"Donald Hamblock","id":1948523233,"id_str":"1948523233","indices":[17,21]}],"urls":[]},"favorited":false,"retweeted":false,"lang":"en"}],"search_metadata":{"completed_in":0.03,"max_id":576499643120381953,"max_id_str":"576499643120381953","query":"","refresh_url":"?since_id=576499643120381953&q=&geocode=37.8052256%2C-122.4102033%2C5mi&include_entities=1","count":15,"since_id":0,"since_id_str":"0"}}